LICENSE
MANIFEST.in
README.rst
setup.py
django_tinsel/__init__.py
django_tinsel/decorators.py
django_tinsel/exceptions.py
django_tinsel/utils.py
django_tinsel.egg-info/PKG-INFO
django_tinsel.egg-info/SOURCES.txt
django_tinsel.egg-info/dependency_links.txt
django_tinsel.egg-info/requires.txt
django_tinsel.egg-info/top_level.txt